sim_VM3000.srcs/sources_1/imports/src/prom.v
module prom(
           input wire clk,
           input wire [2:0] pidx,
           input wire SW,
           output wire LED_pdm,
           output reg out_pattern
       );

wire [7:0] pattern;

assign pattern = SW ? 8'b0101_1010 : 8'b1111_1111;

always @(*) begin
    case (pidx)
        3'b000:
            out_pattern = pattern[0];
        3'b001:
            out_pattern = pattern[1];
        3'b010:
            out_pattern = pattern[2];
        3'b011:
            out_pattern = pattern[3];
        3'b100:
            out_pattern = pattern[4];
        3'b101:
            out_pattern = pattern[5];
        3'b110:
            out_pattern = pattern[6];
        3'b111:
            out_pattern = pattern[7];
    endcase
	//out_pattern <= pattern[2];
end


assign LED_pdm = out_pattern;

endmodule

sim_VM3000.srcs/sources_1/imports/src/sysctrl.v
module sysctrl(
		   input wire rst,
           input wire pdm_clk,
           output wire LED_clk,
           output reg [2:0] pidx	//memory_idx
       );


//pidx   給pattern計數用的
always @(posedge pdm_clk or posedge rst) begin
	if(rst) pidx <= 1'b0;
	else if(pidx < 3'd7)
	pidx <= pidx + 1'b1;
	else if(pidx == 3'd7)
	pidx <= 3'd0;
end
	 
assign LED_clk = pdm_clk;

endmodule

sim_VM3000.srcs/sources_1/imports/src/pdm.v
module vm3000(
           input wire PDMclk,
           input wire SW,
		   input wire rst,
           output wire LED_clk,
           output wire LED_pdm,
           output wire pdm_signal
       );

wire [2:0]  pidx;		//pattern addr

//TODO: control module

sysctrl ctrl_m(
            .pdm_clk(PDMclk),
            .LED_clk(LED_clk),
            .pidx(pidx),
			.rst(rst)
        );

prom prom_m(
         .clk(PDMclk),
         .pidx(pidx),
         .SW(SW),
         .LED_pdm(LED_pdm),
         .out_pattern(pdm_signal)
     );

endmodule

sim_VM3000.srcs/sources_1/imports/src/tb.v
`include "pdm.v"
`include "sysctrl.v"
`include "prom.v"

module tb;

reg pdmclk;
reg SW;
wire pdm_signal;
reg rst;
wire led0;
wire led1;

vm3000 pdm(
           .PDMclk(pdmclk),
		   .SW(SW),
           .LED_clk(led0),
           .LED_pdm(led1),
           .rst(rst),
           .pdm_signal(pdm_signal)
       );

initial begin
    pdmclk = 0;
	rst = 0;
	SW = 1;
    forever begin
        #333
         pdmclk = 1;
        $display("pdm_signal = %b , led0 = %b , led1 = %b , rst = %b\n", pdm_signal , led0 , led1 , rst);
        #333
         pdmclk = 0;
        $display("pdm_signal = %b , led0 = %b , led1 = %b , rst = %b\n", pdm_signal , led0 , led1 , rst);
    end
end

initial begin
	#10000 rst = 1;
	#10100 rst = 0;
end

initial begin
    $dumpfile("dump.vcd");
    $dumpvars;
	#1000000 $finish;
end

endmodule

sim_VM3000.srcs/sources_1/imports/src/dump.vcd
$date
	Tue Dec 15 18:29:05 2020
$end
$version
	Icarus Verilog
$end
$timescale
	1s
$end
$scope module tb $end
$var wire 1 ! pdm_signal $end
$var wire 1 " led1 $end
$var wire 1 # led0 $end
$var reg 1 $ SW $end
$var reg 1 % pdmclk $end
$var reg 1 & rst $end
$scope module pdm $end
$var wire 1 % PDMclk $end
$var wire 1 $ SW $end
$var wire 1 & rst $end
$var wire 3 ' pidx [2:0] $end
$var wire 1 ! pdm_signal $end
$var wire 1 " LED_pdm $end
$var wire 1 # LED_clk $end
$scope module ctrl_m $end
$var wire 1 # LED_clk $end
$var wire 1 % pdm_clk $end
$var wire 1 & rst $end
$var reg 3 ( pidx [2:0] $end
$upscope $end
$scope module prom_m $end
$var wire 1 " LED_pdm $end
$var wire 1 $ SW $end
$var wire 1 % clk $end
$var wire 3 ) pidx [2:0] $end
$var wire 8 * pattern [7:0] $end
$var reg 1 ! out_pattern $end
$upscope $end
$upscope $end
$upscope $end
$enddefinitions $end
#0
$dumpvars
b1011010 *
bx )
bx (
bx '
0&
0%
1$
0#
x"
x!
$end
#333
1#
1%
#666
0#
0%
#999
1#
1%
#1332
0#
0%
#1665
1#
1%
#1998
0#
0%
#2331
1#
1%
#2664
0#
0%
#2997
1#
1%
#3330
0#
0%
#3663
1#
1%
#3996
0#
0%
#4329
1#
1%
#4662
0#
0%
#4995
1#
1%
#5328
0#
0%
#5661
1#
1%
#5994
0#
0%
#6327
1#
1%
#6660
0#
0%
#6993
1#
1%
#7326
0#
0%
#7659
1#
1%
#7992
0#
0%
#8325
1#
1%
#8658
0#
0%
#8991
1#
1%
#9324
0#
0%
#9657
1#
1%
#9990
0#
0%
#10000
0"
0!
b0 '
b0 (
b0 )
1&
#10323
1#
1%
#10656
0#
0%
#10989
1#
1%
#11322
0#
0%
#11655
1#
1%
#11988
0#
0%
#12321
1#
1%
#12654
0#
0%
#12987
1#
1%
#13320
0#
0%
#13653
1#
1%
#13986
0#
0%
#14319
1#
1%
#14652
0#
0%
#14985
1#
1%
#15318
0#
0%
#15651
1#
1%
#15984
0#
0%
#16317
1#
1%
#16650
0#
0%
#16983
1#
1%
#17316
0#
0%
#17649
1#
1%
#17982
0#
0%
#18315
1#
1%
#18648
0#
0%
#18981
1#
1%
#19314
0#
0%
#19647
1#
1%
#19980
0#
0%
#20100
0&
#20313
1"
1!
b1 '
b1 (
b1 )
1#
1%
#20646
0#
0%
#20979
0"
0!
b10 '
b10 (
b10 )
1#
1%
#21312
0#
0%
#21645
1"
1!
b11 '
b11 (
b11 )
1#
1%
#21978
0#
0%
#22311
b100 '
b100 (
b100 )
1#
1%
#22644
0#
0%
#22977
0"
0!
b101 '
b101 (
b101 )
1#
1%
#23310
0#
0%
#23643
1"
1!
b110 '
b110 (
b110 )
1#
1%
#23976
0#
0%
#24309
0"
0!
b111 '
b111 (
b111 )
1#
1%
#24642
0#
0%
#24975
b0 '
b0 (
b0 )
1#
1%
#25308
0#
0%
#25641
1"
1!
b1 '
b1 (
b1 )
1#
1%
#25974
0#
0%
#26307
0"
0!
b10 '
b10 (
b10 )
1#
1%
#26640
0#
0%
#26973
1"
1!
b11 '
b11 (
b11 )
1#
1%
#27306
0#
0%
#27639
b100 '
b100 (
b100 )
1#
1%
#27972
0#
0%
#28305
0"
0!
b101 '
b101 (
b101 )
1#
1%
#28638
0#
0%
#28971
1"
1!
b110 '
b110 (
b110 )
1#
1%
#29304
0#
0%
#29637
0"
0!
b111 '
b111 (
b111 )
1#
1%
#29970
0#
0%
#30303
b0 '
b0 (
b0 )
1#
1%
#30636
0#
0%
#30969
1"
1!
b1 '
b1 (
b1 )
1#
1%
#31302
0#
0%
#31635
0"
0!
b10 '
b10 (
b10 )
1#
1%
#31968
0#
0%
#32301
1"
1!
b11 '
b11 (
b11 )
1#
1%
#32634
0#
0%
#32967
b100 '
b100 (
b100 )
1#
1%
#33300
0#
0%
#33633
0"
0!
b101 '
b101 (
b101 )
1#
1%
#33966
0#
0%
#34299
1"
1!
b110 '
b110 (
b110 )
1#
1%
#34632
0#
0%
#34965
0"
0!
b111 '
b111 (
b111 )
1#
1%
#35298
0#
0%
#35631
b0 '
b0 (
b0 )
1#
1%
#35964
0#
0%
#36297
1"
1!
b1 '
b1 (
b1 )
1#
1%
#36630
0#
0%
#36963
0"
0!
b10 '
b10 (
b10 )
1#
1%
#37296
0#
0%
#37629
1"
1!
b11 '
b11 (
b11 )
1#
1%
#37962
0#
0%
#38295
b100 '
b100 (
b100 )
1#
1%
#38628
0#
0%
#38961
0"
0!
b101 '
b101 (
b101 )
1#
1%
#39294
0#
0%
#39627
1"
1!
b110 '
b110 (
b110 )
1#
1%
#39960
0#
0%
#40293
0"
0!
b111 '
b111 (
b111 )
1#
1%
#40626
0#
0%
#40959
b0 '
b0 (
b0 )
1#
1%
#41292
0#
0%
#41625
1"
1!
b1 '
b1 (
b1 )
1#
1%
#41958
0#
0%
#42291
0"
0!
b10 '
b10 (
b10 )
1#
1%
#42624
0#
0%
#42957
1"
1!
b11 '
b11 (
b11 )
1#
1%
#43290
0#
0%
#43623
b100 '
b100 (
b100 )
1#
1%
#43956
0#
0%
#44289
0"
0!
b101 '
b101 (
b101 )
1#
1%
#44622
0#
0%
#44955
1"
1!
b110 '
b110 (
b110 )
1#
1%
#45288
0#
0%
#45621
0"
0!
b111 '
b111 (
b111 )
1#
1%
#45954
0#
0%
#46287
b0 '
b0 (
b0 )
1#
1%
#46620
0#
0%
#46953
1"
1!
b1 '
b1 (
b1 )
1#
1%
#47286
0#
0%
#47619
0"
0!
b10 '
b10 (
b10 )
1#
1%
#47952
0#
0%
#48285
1"
1!
b11 '
b11 (
b11 )
1#
1%
#48618
0#
0%
#48951
b100 '
b100 (
b100 )
1#
1%
#49284
0#
0%
#49617
0"
0!
b101 '
b101 (
b101 )
1#
1%
#49950
0#
0%
#50283
1"
1!
b110 '
b110 (
b110 )
1#
1%
#50616
0#
0%
#50949
0"
0!
b111 '
b111 (
b111 )
1#
1%
#51282
0#
0%
#51615
b0 '
b0 (
b0 )
1#
1%
#51948
0#
0%
#52281
1"
1!
b1 '
b1 (
b1 )
1#
1%
#52614
0#
0%
#52947
0"
0!
b10 '
b10 (
b10 )
1#
1%
#53280
0#
0%
#53613
1"
1!
b11 '
b11 (
b11 )
1#
1%
#53946
0#
0%
#54279
b100 '
b100 (
b100 )
1#
1%
#54612
0#
0%
#54945
0"
0!
b101 '
b101 (
b101 )
1#
1%
#55278
0#
0%
#55611
1"
1!
b110 '
b110 (
b110 )
1#
1%
#55944
0#
0%
#56277
0"
0!
b111 '
b111 (
b111 )
1#
1%
#56610
0#
0%
#56943
b0 '
b0 (
b0 )
1#
1%
#57276
0#
0%
#57609
1"
1!
b1 '
b1 (
b1 )
1#
1%
#57942
0#
0%
#58275
0"
0!
b10 '
b10 (
b10 )
1#
1%
#58608
0#
0%
#58941
1"
1!
b11 '
b11 (
b11 )
1#
1%
#59274
0#
0%
#59607
b100 '
b100 (
b100 )
1#
1%
#59940
0#
0%
#60273
0"
0!
b101 '
b101 (
b101 )
1#
1%
#60606
0#
0%
#60939
1"
1!
b110 '
b110 (
b110 )
1#
1%
#61272
0#
0%
#61605
0"
0!
b111 '
b111 (
b111 )
1#
1%
#61938
0#
0%
#62271
b0 '
b0 (
b0 )
1#
1%
#62604
0#
0%
#62937
1"
1!
b1 '
b1 (
b1 )
1#
1%
#63270
0#
0%
#63603
0"
0!
b10 '
b10 (
b10 )
1#
1%
#63936
0#
0%
#64269
1"
1!
b11 '
b11 (
b11 )
1#
1%
#64602
0#
0%
#64935
b100 '
b100 (
b100 )
1#
1%
#65268
0#
0%
#65601
0"
0!
b101 '
b101 (
b101 )
1#
1%
#65934
0#
0%
#66267
1"
1!
b110 '
b110 (
b110 )
1#
1%
#66600
0#
0%
#66933
0"
0!
b111 '
b111 (
b111 )
1#
1%
#67266
0#
0%
#67599
b0 '
b0 (
b0 )
1#
1%
#67932
0#
0%
#68265
1"
1!
b1 '
b1 (
b1 )
1#
1%
#68598
0#
0%
#68931
0"
0!
b10 '
b10 (
b10 )
1#
1%
#69264
0#
0%
#69597
1"
1!
b11 '
b11 (
b11 )
1#
1%
#69930
0#
0%
#70263
b100 '
b100 (
b100 )
1#
1%
#70596
0#
0%
#70929
0"
0!
b101 '
b101 (
b101 )
1#
1%
#71262
0#
0%
#71595
1"
1!
b110 '
b110 (
b110 )
1#
1%
#71928
0#
0%
#72261
0"
0!
b111 '
b111 (
b111 )
1#
1%
#72594
0#
0%
#72927
b0 '
b0 (
b0 )
1#
1%
#73260
0#
0%
#73593
1"
1!
b1 '
b1 (
b1 )
1#
1%
#73926
0#
0%
#74259
0"
0!
b10 '
b10 (
b10 )
1#
1%
#74592
0#
0%
#74925
1"
1!
b11 '
b11 (
b11 )
1#
1%
#75258
0#
0%
#75591
b100 '
b100 (
b100 )
1#
1%
#75924
0#
0%
#76257
0"
0!
b101 '
b101 (
b101 )
1#
1%
#76590
0#
0%
#76923
1"
1!
b110 '
b110 (
b110 )
1#
1%
#77256
0#
0%
#77589
0"
0!
b111 '
b111 (
b111 )
1#
1%
#77922
0#
0%
#78255
b0 '
b0 (
b0 )
1#
1%
#78588
0#
0%
#78921
1"
1!
b1 '
b1 (
b1 )
1#
1%
#79254
0#
0%
#79587
0"
0!
b10 '
b10 (
b10 )
1#
1%
#79920
0#
0%
#80253
1"
1!
b11 '
b11 (
b11 )
1#
1%
#80586
0#
0%
#80919
b100 '
b100 (
b100 )
1#
1%
#81252
0#
0%
#81585
0"
0!
b101 '
b101 (
b101 )
1#
1%
#81918
0#
0%
#82251
1"
1!
b110 '
b110 (
b110 )
1#
1%
#82584
0#
0%
#82917
0"
0!
b111 '
b111 (
b111 )
1#
1%
#83250
0#
0%
#83583
b0 '
b0 (
b0 )
1#
1%
#83916
0#
0%
#84249
1"
1!
b1 '
b1 (
b1 )
1#
1%
#84582
0#
0%
#84915
0"
0!
b10 '
b10 (
b10 )
1#
1%
#85248
0#
0%
#85581
1"
1!
b11 '
b11 (
b11 )
1#
1%
#85914
0#
0%
#86247
b100 '
b100 (
b100 )
1#
1%
#86580
0#
0%
#86913
0"
0!
b101 '
b101 (
b101 )
1#
1%
#87246
0#
0%
#87579
1"
1!
b110 '
b110 (
b110 )
1#
1%
#87912
0#
0%
#88245
0"
0!
b111 '
b111 (
b111 )
1#
1%
#88578
0#
0%
#88911
b0 '
b0 (
b0 )
1#
1%
#89244
0#
0%
#89577
1"
1!
b1 '
b1 (
b1 )
1#
1%
#89910
0#
0%
#90243
0"
0!
b10 '
b10 (
b10 )
1#
1%
#90576
0#
0%
#90909
1"
1!
b11 '
b11 (
b11 )
1#
1%
#91242
0#
0%
#91575
b100 '
b100 (
b100 )
1#
1%
#91908
0#
0%
#92241
0"
0!
b101 '
b101 (
b101 )
1#
1%
#92574
0#
0%
#92907
1"
1!
b110 '
b110 (
b110 )
1#
1%
#93240
0#
0%
#93573
0"
0!
b111 '
b111 (
b111 )
1#
1%
#93906
0#
0%
#94239
b0 '
b0 (
b0 )
1#
1%
#94572
0#
0%
#94905
1"
1!
b1 '
b1 (
b1 )
1#
1%
#95238
0#
0%
#95571
0"
0!
b10 '
b10 (
b10 )
1#
1%
#95904
0#
0%
#96237
1"
1!
b11 '
b11 (
b11 )
1#
1%
#96570
0#
0%
#96903
b100 '
b100 (
b100 )
1#
1%
#97236
0#
0%
#97569
0"
0!
b101 '
b101 (
b101 )
1#
1%
#97902
0#
0%
#98235
1"
1!
b110 '
b110 (
b110 )
1#
1%
#98568
0#
0%
#98901
0"
0!
b111 '
b111 (
b111 )
1#
1%
#99234
0#
0%
#99567
b0 '
b0 (
b0 )
1#
1%
#99900
0#
0%
#100233
1"
1!
b1 '
b1 (
b1 )
1#
1%
#100566
0#
0%
#100899
0"
0!
b10 '
b10 (
b10 )
1#
1%
#101232
0#
0%
#101565
1"
1!
b11 '
b11 (
b11 )
1#
1%
#101898
0#
0%
#102231
b100 '
b100 (
b100 )
1#
1%
#102564
0#
0%
#102897
0"
0!
b101 '
b101 (
b101 )
1#
1%
#103230
0#
0%
#103563
1"
1!
b110 '
b110 (
b110 )
1#
1%
#103896
0#
0%
#104229
0"
0!
b111 '
b111 (
b111 )
1#
1%
#104562
0#
0%
#104895
b0 '
b0 (
b0 )
1#
1%
#105228
0#
0%
#105561
1"
1!
b1 '
b1 (
b1 )
1#
1%
#105894
0#
0%
#106227
0"
0!
b10 '
b10 (
b10 )
1#
1%
#106560
0#
0%
#106893
1"
1!
b11 '
b11 (
b11 )
1#
1%
#107226
0#
0%
#107559
b100 '
b100 (
b100 )
1#
1%
#107892
0#
0%
#108225
0"
0!
b101 '
b101 (
b101 )
1#
1%
#108558
0#
0%
#108891
1"
1!
b110 '
b110 (
b110 )
1#
1%
#109224
0#
0%
#109557
0"
0!
b111 '
b111 (
b111 )
1#
1%
#109890
0#
0%
#110223
b0 '
b0 (
b0 )
1#
1%
#110556
0#
0%
#110889
1"
1!
b1 '
b1 (
b1 )
1#
1%
#111222
0#
0%
#111555
0"
0!
b10 '
b10 (
b10 )
1#
1%
#111888
0#
0%
#112221
1"
1!
b11 '
b11 (
b11 )
1#
1%
#112554
0#
0%
#112887
b100 '
b100 (
b100 )
1#
1%
#113220
0#
0%
#113553
0"
0!
b101 '
b101 (
b101 )
1#
1%
#113886
0#
0%
#114219
1"
1!
b110 '
b110 (
b110 )
1#
1%
#114552
0#
0%
#114885
0"
0!
b111 '
b111 (
b111 )
1#
1%
#115218
0#
0%
#115551
b0 '
b0 (
b0 )
1#
1%
#115884
0#
0%
#116217
1"
1!
b1 '
b1 (
b1 )
1#
1%
#116550
0#
0%
#116883
0"
0!
b10 '
b10 (
b10 )
1#
1%
#117216
0#
0%
#117549
1"
1!
b11 '
b11 (
b11 )
1#
1%
#117882
0#
0%
#118215
b100 '
b100 (
b100 )
1#
1%
#118548
0#
0%
#118881
0"
0!
b101 '
b101 (
b101 )
1#
1%
#119214
0#
0%
#119547
1"
1!
b110 '
b110 (
b110 )
1#
1%
#119880
0#
0%
#120213
0"
0!
b111 '
b111 (
b111 )
1#
1%
#120546
0#
0%
#120879
b0 '
b0 (
b0 )
1#
1%
#121212
0#
0%
#121545
1"
1!
b1 '
b1 (
b1 )
1#
1%
#121878
0#
0%
#122211
0"
0!
b10 '
b10 (
b10 )
1#
1%
#122544
0#
0%
#122877
1"
1!
b11 '
b11 (
b11 )
1#
1%
#123210
0#
0%
#123543
b100 '
b100 (
b100 )
1#
1%
#123876
0#
0%
#124209
0"
0!
b101 '
b101 (
b101 )
1#
1%
#124542
0#
0%
#124875
1"
1!
b110 '
b110 (
b110 )
1#
1%
#125208
0#
0%
#125541
0"
0!
b111 '
b111 (
b111 )
1#
1%
#125874
0#
0%
#126207
b0 '
b0 (
b0 )
1#
1%
#126540
0#
0%
#126873
1"
1!
b1 '
b1 (
b1 )
1#
1%
#127206
0#
0%
#127539
0"
0!
b10 '
b10 (
b10 )
1#
1%
#127872
0#
0%
#128205
1"
1!
b11 '
b11 (
b11 )
1#
1%
#128538
0#
0%
#128871
b100 '
b100 (
b100 )
1#
1%
#129204
0#
0%
#129537
0"
0!
b101 '
b101 (
b101 )
1#
1%
#129870
0#
0%
#130203
1"
1!
b110 '
b110 (
b110 )
1#
1%
#130536
0#
0%
#130869
0"
0!
b111 '
b111 (
b111 )
1#
1%
#131202
0#
0%
#131535
b0 '
b0 (
b0 )
1#
1%
#131868
0#
0%
#132201
1"
1!
b1 '
b1 (
b1 )
1#
1%
#132534
0#
0%
#132867
0"
0!
b10 '
b10 (
b10 )
1#
1%
#133200
0#
0%
#133533
1"
1!
b11 '
b11 (
b11 )
1#
1%
#133866
0#
0%
#134199
b100 '
b100 (
b100 )
1#
1%
#134532
0#
0%
#134865
0"
0!
b101 '
b101 (
b101 )
1#
1%
#135198
0#
0%
#135531
1"
1!
b110 '
b110 (
b110 )
1#
1%
#135864
0#
0%
#136197
0"
0!
b111 '
b111 (
b111 )
1#
1%
#136530
0#
0%
#136863
b0 '
b0 (
b0 )
1#
1%
#137196
0#
0%
#137529
1"
1!
b1 '
b1 (
b1 )
1#
1%
#137862
0#
0%
#138195
0"
0!
b10 '
b10 (
b10 )
1#
1%
#138528
0#
0%
#138861
1"
1!
b11 '
b11 (
b11 )
1#
1%
#139194
0#
0%
#139527
b100 '
b100 (
b100 )
1#
1%
#139860
0#
0%
#140193
0"
0!
b101 '
b101 (
b101 )
1#
1%
#140526
0#
0%
#140859
1"
1!
b110 '
b110 (
b110 )
1#
1%
#141192
0#
0%
#141525
0"
0!
b111 '
b111 (
b111 )
1#
1%
#141858
0#
0%
#142191
b0 '
b0 (
b0 )
1#
1%
#142524
0#
0%
#142857
1"
1!
b1 '
b1 (
b1 )
1#
1%
#143190
0#
0%
#143523
0"
0!
b10 '
b10 (
b10 )
1#
1%
#143856
0#
0%
#144189
1"
1!
b11 '
b11 (
b11 )
1#
1%
#144522
0#
0%
#144855
b100 '
b100 (
b100 )
1#
1%
#145188
0#
0%
#145521
0"
0!
b101 '
b101 (
b101 )
1#
1%
#145854
0#
0%
#146187
1"
1!
b110 '
b110 (
b110 )
1#
1%
#146520
0#
0%
#146853
0"
0!
b111 '
b111 (
b111 )
1#
1%
#147186
0#
0%
#147519
b0 '
b0 (
b0 )
1#
1%
#147852
0#
0%
#148185
1"
1!
b1 '
b1 (
b1 )
1#
1%
#148518
0#
0%
#148851
0"
0!
b10 '
b10 (
b10 )
1#
1%
#149184
0#
0%
#149517
1"
1!
b11 '
b11 (
b11 )
1#
1%
#149850
0#
0%
#150183
b100 '
b100 (
b100 )
1#
1%
#150516
0#
0%
#150849
0"
0!
b101 '
b101 (
b101 )
1#
1%
#151182
0#
0%
#151515
1"
1!
b110 '
b110 (
b110 )
1#
1%
#151848
0#
0%
#152181
0"
0!
b111 '
b111 (
b111 )
1#
1%
#152514
0#
0%
#152847
b0 '
b0 (
b0 )
1#
1%
#153180
0#
0%
#153513
1"
1!
b1 '
b1 (
b1 )
1#
1%
#153846
0#
0%
#154179
0"
0!
b10 '
b10 (
b10 )
1#
1%
#154512
0#
0%
#154845
1"
1!
b11 '
b11 (
b11 )
1#
1%
#155178
0#
0%
#155511
b100 '
b100 (
b100 )
1#
1%
#155844
0#
0%
#156177
0"
0!
b101 '
b101 (
b101 )
1#
1%
#156510
0#
0%
#156843
1"
1!
b110 '
b110 (
b110 )
1#
1%
#157176
0#
0%
#157509
0"
0!
b111 '
b111 (
b111 )
1#
1%
#157842
0#
0%
#158175
b0 '
b0 (
b0 )
1#
1%
#158508
0#
0%
#158841
1"
1!
b1 '
b1 (
b1 )
1#
1%
#159174
0#
0%
#159507
0"
0!
b10 '
b10 (
b10 )
1#
1%
#159840
0#
0%
#160173
1"
1!
b11 '
b11 (
b11 )
1#
1%
#160506
0#
0%
#160839
b100 '
b100 (
b100 )
1#
1%
#161172
0#
0%
#161505
0"
0!
b101 '
b101 (
b101 )
1#
1%
#161838
0#
0%
#162171
1"
1!
b110 '
b110 (
b110 )
1#
1%
#162504
0#
0%
#162837
0"
0!
b111 '
b111 (
b111 )
1#
1%
#163170
0#
0%
#163503
b0 '
b0 (
b0 )
1#
1%
#163836
0#
0%
#164169
1"
1!
b1 '
b1 (
b1 )
1#
1%
#164502
0#
0%
#164835
0"
0!
b10 '
b10 (
b10 )
1#
1%
#165168
0#
0%
#165501
1"
1!
b11 '
b11 (
b11 )
1#
1%
#165834
0#
0%
#166167
b100 '
b100 (
b100 )
1#
1%
#166500
0#
0%
#166833
0"
0!
b101 '
b101 (
b101 )
1#
1%
#167166
0#
0%
#167499
1"
1!
b110 '
b110 (
b110 )
1#
1%
#167832
0#
0%
#168165
0"
0!
b111 '
b111 (
b111 )
1#
1%
#168498
0#
0%
#168831
b0 '
b0 (
b0 )
1#
1%
#169164
0#
0%
#169497
1"
1!
b1 '
b1 (
b1 )
1#
1%
#169830
0#
0%
#170163
0"
0!
b10 '
b10 (
b10 )
1#
1%
#170496
0#
0%
#170829
1"
1!
b11 '
b11 (
b11 )
1#
1%
#171162
0#
0%
#171495
b100 '
b100 (
b100 )
1#
1%
#171828
0#
0%
#172161
0"
0!
b101 '
b101 (
b101 )
1#
1%
#172494
0#
0%
#172827
1"
1!
b110 '
b110 (
b110 )
1#
1%
#173160
0#
0%
#173493
0"
0!
b111 '
b111 (
b111 )
1#
1%
#173826
0#
0%
#174159
b0 '
b0 (
b0 )
1#
1%
#174492
0#
0%
#174825
1"
1!
b1 '
b1 (
b1 )
1#
1%
#175158
0#
0%
#175491
0"
0!
b10 '
b10 (
b10 )
1#
1%
#175824
0#
0%
#176157
1"
1!
b11 '
b11 (
b11 )
1#
1%
#176490
0#
0%
#176823
b100 '
b100 (
b100 )
1#
1%
#177156
0#
0%
#177489
0"
0!
b101 '
b101 (
b101 )
1#
1%
#177822
0#
0%
#178155
1"
1!
b110 '
b110 (
b110 )
1#
1%
#178488
0#
0%
#178821
0"
0!
b111 '
b111 (
b111 )
1#
1%
#179154
0#
0%
#179487
b0 '
b0 (
b0 )
1#
1%
#179820
0#
0%
#180153
1"
1!
b1 '
b1 (
b1 )
1#
1%
#180486
0#
0%
#180819
0"
0!
b10 '
b10 (
b10 )
1#
1%
#181152
0#
0%
#181485
1"
1!
b11 '
b11 (
b11 )
1#
1%
#181818
0#
0%
#182151
b100 '
b100 (
b100 )
1#
1%
#182484
0#
0%
#182817
0"
0!
b101 '
b101 (
b101 )
1#
1%
#183150
0#
0%
#183483
1"
1!
b110 '
b110 (
b110 )
1#
1%
#183816
0#
0%
#184149
0"
0!
b111 '
b111 (
b111 )
1#
1%
#184482
0#
0%
#184815
b0 '
b0 (
b0 )
1#
1%
#185148
0#
0%
#185481
1"
1!
b1 '
b1 (
b1 )
1#
1%
#185814
0#
0%
#186147
0"
0!
b10 '
b10 (
b10 )
1#
1%
#186480
0#
0%
#186813
1"
1!
b11 '
b11 (
b11 )
1#
1%
#187146
0#
0%
#187479
b100 '
b100 (
b100 )
1#
1%
#187812
0#
0%
#188145
0"
0!
b101 '
b101 (
b101 )
1#
1%
#188478
0#
0%
#188811
1"
1!
b110 '
b110 (
b110 )
1#
1%
#189144
0#
0%
#189477
0"
0!
b111 '
b111 (
b111 )
1#
1%
#189810
0#
0%
#190143
b0 '
b0 (
b0 )
1#
1%
#190476
0#
0%
#190809
1"
1!
b1 '
b1 (
b1 )
1#
1%
#191142
0#
0%
#191475
0"
0!
b10 '
b10 (
b10 )
1#
1%
#191808
0#
0%
#192141
1"
1!
b11 '
b11 (
b11 )
1#
1%
#192474
0#
0%
#192807
b100 '
b100 (
b100 )
1#
1%
#193140
0#
0%
#193473
0"
0!
b101 '
b101 (
b101 )
1#
1%
#193806
0#
0%
#194139
1"
1!
b110 '
b110 (
b110 )
1#
1%
#194472
0#
0%
#194805
0"
0!
b111 '
b111 (
b111 )
1#
1%
#195138
0#
0%
#195471
b0 '
b0 (
b0 )
1#
1%
#195804
0#
0%
#196137
1"
1!
b1 '
b1 (
b1 )
1#
1%
#196470
0#
0%
#196803
0"
0!
b10 '
b10 (
b10 )
1#
1%
#197136
0#
0%
#197469
1"
1!
b11 '
b11 (
b11 )
1#
1%
#197802
0#
0%
#198135
b100 '
b100 (
b100 )
1#
1%
#198468
0#
0%
#198801
0"
0!
b101 '
b101 (
b101 )
1#
1%
#199134
0#
0%
#199467
1"
1!
b110 '
b110 (
b110 )
1#
1%
#199800
0#
0%
#200133
0"
0!
b111 '
b111 (
b111 )
1#
1%
#200466
0#
0%
#200799
b0 '
b0 (
b0 )
1#
1%
#201132
0#
0%
#201465
1"
1!
b1 '
b1 (
b1 )
1#
1%
#201798
0#
0%
#202131
0"
0!
b10 '
b10 (
b10 )
1#
1%
#202464
0#
0%
#202797
1"
1!
b11 '
b11 (
b11 )
1#
1%
#203130
0#
0%
#203463
b100 '
b100 (
b100 )
1#
1%
#203796
0#
0%
#204129
0"
0!
b101 '
b101 (
b101 )
1#
1%
#204462
0#
0%
#204795
1"
1!
b110 '
b110 (
b110 )
1#
1%
#205128
0#
0%
#205461
0"
0!
b111 '
b111 (
b111 )
1#
1%
#205794
0#
0%
#206127
b0 '
b0 (
b0 )
1#
1%
#206460
0#
0%
#206793
1"
1!
b1 '
b1 (
b1 )
1#
1%
#207126
0#
0%
#207459
0"
0!
b10 '
b10 (
b10 )
1#
1%
#207792
0#
0%
#208125
1"
1!
b11 '
b11 (
b11 )
1#
1%
#208458
0#
0%
#208791
b100 '
b100 (
b100 )
1#
1%
#209124
0#
0%
#209457
0"
0!
b101 '
b101 (
b101 )
1#
1%
#209790
0#
0%
#210123
1"
1!
b110 '
b110 (
b110 )
1#
1%
#210456
0#
0%
#210789
0"
0!
b111 '
b111 (
b111 )
1#
1%
#211122
0#
0%
#211455
b0 '
b0 (
b0 )
1#
1%
#211788
0#
0%
#212121
1"
1!
b1 '
b1 (
b1 )
1#
1%
#212454
0#
0%
#212787
0"
0!
b10 '
b10 (
b10 )
1#
1%
#213120
0#
0%
#213453
1"
1!
b11 '
b11 (
b11 )
1#
1%
#213786
0#
0%
#214119
b100 '
b100 (
b100 )
1#
1%
#214452
0#
0%
#214785
0"
0!
b101 '
b101 (
b101 )
1#
1%
#215118
0#
0%
#215451
1"
1!
b110 '
b110 (
b110 )
1#
1%
#215784
0#
0%
#216117
0"
0!
b111 '
b111 (
b111 )
1#
1%
#216450
0#
0%
#216783
b0 '
b0 (
b0 )
1#
1%
#217116
0#
0%
#217449
1"
1!
b1 '
b1 (
b1 )
1#
1%
#217782
0#
0%
#218115
0"
0!
b10 '
b10 (
b10 )
1#
1%
#218448
0#
0%
#218781
1"
1!
b11 '
b11 (
b11 )
1#
1%
#219114
0#
0%
#219447
b100 '
b100 (
b100 )
1#
1%
#219780
0#
0%
#220113
0"
0!
b101 '
b101 (
b101 )
1#
1%
#220446
0#
0%
#220779
1"
1!
b110 '
b110 (
b110 )
1#
1%
#221112
0#
0%
#221445
0"
0!
b111 '
b111 (
b111 )
1#
1%
#221778
0#
0%
#222111
b0 '
b0 (
b0 )
1#
1%
#222444
0#
0%
#222777
1"
1!
b1 '
b1 (
b1 )
1#
1%
#223110
0#
0%
#223443
0"
0!
b10 '
b10 (
b10 )
1#
1%
#223776
0#
0%
#224109
1"
1!
b11 '
b11 (
b11 )
1#
1%
#224442
0#
0%
#224775
b100 '
b100 (
b100 )
1#
1%
#225108
0#
0%
#225441
0"
0!
b101 '
b101 (
b101 )
1#
1%
#225774
0#
0%
#226107
1"
1!
b110 '
b110 (
b110 )
1#
1%
#226440
0#
0%
#226773
0"
0!
b111 '
b111 (
b111 )
1#
1%
#227106
0#
0%
#227439
b0 '
b0 (
b0 )
1#
1%
#227772
0#
0%
#228105
1"
1!
b1 '
b1 (
b1 )
1#
1%
#228438
0#
0%
#228771
0"
0!
b10 '
b10 (
b10 )
1#
1%
#229104
0#
0%
#229437
1"
1!
b11 '
b11 (
b11 )
1#
1%
#229770
0#
0%
